dbrownell_Common/ContextlibEx.py
dbrownell_Common/ExecuteTasks.py
dbrownell_Common/InflectEx.py
dbrownell_Common/PathEx.py
dbrownell_Common/SubprocessEx.py
dbrownell_Common/TextwrapEx.py
dbrownell_Common/TyperEx.py
dbrownell_Common/Types.py
dbrownell_Common/__init__.py
dbrownell_Common/py.typed
dbrownell_Common/Streams/Capabilities.py
dbrownell_Common/Streams/DoneManager.py
dbrownell_Common/Streams/StreamDecorator.py
dbrownell_Common/Streams/TextWriter.py
dbrownell_Common/Streams/__init__.py
dbrownell_Common/TestHelpers/StreamTestHelpers.py
dbrownell_Common/TestHelpers/__init__.py
dbrownell_common-0.15.1.dist-info/METADATA
dbrownell_common-0.15.1.dist-info/WHEEL
dbrownell_common-0.15.1.dist-info/licenses/LICENSE
dbrownell_common-0.15.1.dist-info/RECORD
