Metadata-Version: 2.4
Name: dbrownell-Common
Version: 0.15.1
Summary: Add your description here
Project-URL: Homepage, https://github.com/davidbrownell/dbrownell_Common
Project-URL: Documentation, https://github.com/davidbrownell/dbrownell_Common
Project-URL: Repository, https://github.com/davidbrownell/dbrownell_Common
Author-email: David Brownell <github@DavidBrownell.com>
License: MIT
License-File: LICENSE
Classifier: Development Status :: 4 - Beta
Classifier: Intended Audience :: Developers
Classifier: License :: OSI Approved :: MIT License
Classifier: Natural Language :: English
Classifier: Operating System :: MacOS
Classifier: Operating System :: Microsoft :: Windows
Classifier: Operating System :: POSIX :: Linux
Classifier: Programming Language :: Python
Classifier: Programming Language :: Python :: 3.10
Classifier: Programming Language :: Python :: 3.11
Classifier: Programming Language :: Python :: 3.12
Classifier: Programming Language :: Python :: 3.13
Classifier: Topic :: Software Development
Classifier: Topic :: System :: System Shells
Classifier: Topic :: Terminals
Classifier: Topic :: Utilities
Requires-Python: >=3.10
Requires-Dist: inflect>=7.5.0
Requires-Dist: rich>=14.0.0
Requires-Dist: typer-config>=1.4.2
Requires-Dist: typer>=0.15.3
